hl7_convert/__init__.py
hl7_convert/client.py
hl7_convert/main.py
hl7_conversion-0.1.1.dist-info/LICENSE
hl7_conversion-0.1.1.dist-info/METADATA
hl7_conversion-0.1.1.dist-info/WHEEL
hl7_conversion-0.1.1.dist-info/entry_points.txt
hl7_conversion-0.1.1.dist-info/top_level.txt
hl7_conversion-0.1.1.dist-info/RECORD
