Metadata-Version: 2.1
Name: hl7-conversion
Version: 0.1.1
Summary: Package to convert HL7 messages to JSON format
Home-page: https://github.com/imran221b/hl7-conversion
Author: Imran Hasan
Author-email: imran221b@gmail.com
License: MIT
Platform: posix
Requires-Dist: Click
Requires-Dist: hl7apy
Provides-Extra: dev
Requires-Dist: black ; extra == 'dev'
Provides-Extra: test
Requires-Dist: pytest ; extra == 'test'
